jinja_to_resume/__init__.py
jinja_to_resume/__main__.py
jinja_to_resume-0.2.0.dist-info/METADATA
jinja_to_resume-0.2.0.dist-info/WHEEL
jinja_to_resume-0.2.0.dist-info/entry_points.txt
jinja_to_resume-0.2.0.dist-info/top_level.txt
jinja_to_resume-0.2.0.dist-info/RECORD
